{
  "country": "DE",
  "id": "5576d5674dab71fc2f8b4568",
  "name": "Herzhaft gefüllte Portobello-Pilz-Burger mit Ofen-Pommes,",
  "seoName": null,
  "category": null,
  "slug": "herzhaft-gefullte-portobello-pilz-burger-mit-ofen-pommes",
  "headline": "Zwiebelade und Crème fraîche-Dip",
  "description": "Wir haben wieder ein vegetarisches Burger-Rezept gefunden, mit dem Du Augen, Geschmacksknospen und Deinem Gaumen eine Freude bereitest. Zudem tust Du Deinen Körper mit den vielen bekannten und noch mehr unbekannten sekundären Pflanzenstoffen etwas Gutes. Guten Appetit!",
  "descriptionHTML": "<p>Wir haben wieder ein vegetarisches Burger-Rezept gefunden, mit dem Du Augen, Geschmacksknospen und Deinem Gaumen eine Freude bereitest. Zudem tust Du Deinen Körper mit den vielen bekannten und noch mehr unbekannten sekundären Pflanzenstoffen etwas Gutes. Guten Appetit!</p>",
  "descriptionMarkdown": "Wir haben wieder ein vegetarisches Burger-Rezept gefunden, mit dem Du Augen, Geschmacksknospen und Deinem Gaumen eine Freude bereitest. Zudem tust Du Deinen Körper mit den vielen bekannten und noch mehr unbekannten sekundären Pflanzenstoffen etwas Gutes. Guten Appetit!",
  "seoDescription": null,
  "comment": null,
  "difficulty": 3,
  "prepTime": "PT35M",
  "totalTime": null,
  "servingSize": 0,
  "createdAt": "2015-06-09T12:00:39+00:00",
  "updatedAt": "2017-03-06T13:39:53+00:00",
  "link": "https://hellofresh.com/recipes/5576d5674dab71fc2f8b4568",
  "imageLink": "https://d3hvwccx09j84u.cloudfront.net/0,0/image/5576d5674dab71fc2f8b4568.jpg",
  "cardLink": "https://ddw4dkk7s1lkt.cloudfront.net/card/5576d5674dab71fc2f8b4568.pdf",
  "videoLink": null,
  "nutrition": [
    {
      "type": "57b42a48b7e8697d4b30530d",
      "name": "Energie (kJ)",
      "amount": 3280,
      "unit": "kJ"
    },
    {
      "type": "57b42a48b7e8697d4b305304",
      "name": "Energie (kcal)",
      "amount": 784,
      "unit": "kcal"
    },
    {
      "type": "57b42a48b7e8697d4b305307",
      "name": "Fett",
      "amount": 30,
      "unit": "g"
    },
    {
      "type": "57b42a48b7e8697d4b305308",
      "name": "davon gesättigte Fettsäuren",
      "amount": 0,
      "unit": "g"
    },
    {
      "type": "57b42a48b7e8697d4b305305",
      "name": "Kohlenhydrate",
      "amount": 97,
      "unit": "g"
    },
    {
      "type": "57b42a48b7e8697d4b305306",
      "name": "davon Zucker",
      "amount": 0,
      "unit": "g"
    },
    {
      "type": "57b42a48b7e8697d4b30530a",
      "name": "Ballaststoffe",
      "amount": 9,
      "unit": "g"
    },
    {
      "type": "57b42a48b7e8697d4b305309",
      "name": "Eiweiß",
      "amount": 23,
      "unit": "g"
    },
    {
      "type": "57b42a48b7e8697d4b30530c",
      "name": "Cholesterol",
      "amount": 0,
      "unit": "mg"
    },
    {
      "type": "57b42a48b7e8697d4b30530b",
      "name": "Salz",
      "amount": 0,
      "unit": "g"
    }
  ],
  "ingredients": [
    {
      "country": "DE",
      "id": "554b25fcfd2cb973608b4567",
      "type": "kartoffeln",
      "name": "Kartoffeln",
      "slug": "kartoffeln",
      "description": null,
      "internalName": null,
      "shipped": true,
      "imageLink": "https://d3hvwccx09j84u.cloudfront.net/200,200/image/554b25fcfd2cb973608b4567.png",
      "usage": 478,
      "hasDuplicatedName": null,
      "allergens": [],
      "family": {
        "id": "58877cf3ed71a76e9c03fc13",
        "type": "potatoes",
        "name": "Kartoffeln",
        "slug": "kartoffeln",
        "description": null,
        "priority": 0,
        "iconLink": "https://d3hvwccx09j84u.cloudfront.net/200,200/ingredient-families/58877cf3ed71a76e9c03fc13-d5b74be4.png",
        "usageByCountry": {
          "AT": 1126,
          "AU": 548,
          "BE": 711,
          "CA": 260,
          "CH": 213,
          "DE": 1009,
          "ER": 81,
          "FR": 197,
          "GB": 773,
          "LU": 934,
          "NL": 814,
          "NZ": 160,
          "ML": 1017,
          "US": 829
        },
        "createdAt": "2017-01-24T16:12:35+00:00",
        "updatedAt": "2017-01-24T16:12:35+00:00"
      }
    },
    {
      "country": "DE",
      "id": "556d72274dab712c498b4568",
      "type": "paprikapulver edelsüß",
      "name": "Paprikapulver edelsüß",
      "slug": "paprikapulver-edelsusz",
      "description": null,
      "internalName": null,
      "shipped": true,
      "imageLink": "https://d3hvwccx09j84u.cloudfront.net/200,200/image/556d72274dab712c498b4568.png",
      "usage": 31,
      "hasDuplicatedName": null,
      "allergens": [],
      "family": {
        "id": "58877cf3ed71a76e9c03fbf8",
        "type": "paprika-powder",
        "name": "Paprikapulver",
        "slug": "paprikapulver",
        "description": null,
        "priority": 0,
        "iconLink": "https://d3hvwccx09j84u.cloudfront.net/200,200/ingredient-families/58877cf3ed71a76e9c03fbf8-57ddbd04.png",
        "usageByCountry": {
          "AT": 105,
          "AU": 15,
          "BE": 162,
          "CA": 6,
          "CH": 26,
          "DE": 105,
          "ER": 1,
          "FR": 42,
          "GB": 35,
          "LU": 213,
          "NL": 182,
          "NZ": 0,
          "ML": 0,
          "US": 31
        },
        "createdAt": "2017-01-24T16:12:35+00:00",
        "updatedAt": "2017-01-24T16:12:35+00:00"
      }
    },
    {
      "country": "DE",
      "id": "55798feb4dab71e4468b4568",
      "type": "portobello-pilze",
      "name": "Portobello-Pilze",
      "slug": "portobello-pilze",
      "description": null,
      "internalName": null,
      "shipped": true,
      "imageLink": "https://d3hvwccx09j84u.cloudfront.net/200,200/ingredients/55798feb4dab71e4468b4568-802d5477.png",
      "usage": 57,
      "hasDuplicatedName": null,
      "allergens": [],
      "family": {
        "id": "58877cf3ed71a76e9c03fbde",
        "type": "mushrooms",
        "name": "Pilze",
        "slug": "pilze",
        "description": null,
        "priority": 0,
        "iconLink": "https://d3hvwccx09j84u.cloudfront.net/200,200/ingredient-families/58877cf3ed71a76e9c03fbde-4d22942c.png",
        "usageByCountry": {
          "AT": 558,
          "AU": 96,
          "BE": 230,
          "CA": 75,
          "CH": 86,
          "DE": 484,
          "ER": 1,
          "FR": 60,
          "GB": 207,
          "LU": 251,
          "NL": 280,
          "NZ": 21,
          "ML": 17,
          "US": 209
        },
        "createdAt": "2017-01-24T16:12:35+00:00",
        "updatedAt": "2017-01-24T16:12:35+00:00"
      }
    },
    {
      "country": "DE",
      "id": "555357a3f8b25e89038b456a",
      "type": "limette",
      "name": "Limette",
      "slug": "limette",
      "description": null,
      "internalName": null,
      "shipped": true,
      "imageLink": "https://d3hvwccx09j84u.cloudfront.net/200,200/image/555357a3f8b25e89038b456a.png",
      "usage": 350,
      "hasDuplicatedName": null,
      "allergens": [],
      "family": {
        "id": "58877cf3ed71a76e9c03fbc8",
        "type": "lime",
        "name": "Limette",
        "slug": "limette",
        "description": null,
        "priority": 0,
        "iconLink": "https://d3hvwccx09j84u.cloudfront.net/200,200/ingredient-families/58877cf3ed71a76e9c03fbc8-7cbce945.png",
        "usageByCountry": {
          "AT": 383,
          "AU": 227,
          "BE": 132,
          "CA": 137,
          "CH": 82,
          "DE": 351,
          "ER": 61,
          "FR": 68,
          "GB": 407,
          "LU": 224,
          "NL": 155,
          "NZ": 63,
          "ML": 87,
          "US": 604
        },
        "createdAt": "2017-01-24T16:12:35+00:00",
        "updatedAt": "2017-01-24T16:12:35+00:00"
      }
    },
    {
      "country": "DE",
      "id": "554b2abcf8b25eef3e8b4573",
      "type": "rote zwiebel",
      "name": "rote Zwiebel",
      "slug": "rote-zwiebel",
      "description": null,
      "internalName": null,
      "shipped": true,
      "imageLink": "https://d3hvwccx09j84u.cloudfront.net/200,200/image/554b2abcf8b25eef3e8b4573.png",
      "usage": 629,
      "hasDuplicatedName": null,
      "allergens": [],
      "family": {
        "id": "58877cf3ed71a76e9c03fbee",
        "type": "onion",
        "name": "Zwiebel",
        "slug": "zwiebel",
        "description": null,
        "priority": 0,
        "iconLink": "https://d3hvwccx09j84u.cloudfront.net/200,200/ingredient-families/58877cf3ed71a76e9c03fbee-34de32d5.png",
        "usageByCountry": {
          "AT": 1698,
          "AU": 1175,
          "BE": 1213,
          "CA": 672,
          "CH": 321,
          "DE": 1582,
          "ER": 152,
          "FR": 334,
          "GB": 1502,
          "LU": 1592,
          "NL": 1429,
          "NZ": 274,
          "ML": 188,
          "US": 2363
        },
        "createdAt": "2017-01-24T16:12:35+00:00",
        "updatedAt": "2017-01-24T16:12:35+00:00"
      }
    },
    {
      "country": "DE",
      "id": "555dbfadf8b25e246a8b4569",
      "type": "rote bete",
      "name": "rote Bete",
      "slug": "rote-bete",
      "description": null,
      "internalName": "rote Bete [RAW]",
      "shipped": true,
      "imageLink": "https://d3hvwccx09j84u.cloudfront.net/200,200/ingredients/555dbfadf8b25e246a8b4569-dba13df7.png",
      "usage": 40,
      "hasDuplicatedName": null,
      "allergens": [],
      "family": {
        "id": "58877cf3ed71a76e9c03fb50",
        "type": "beetroot",
        "name": "Rote Beete",
        "slug": "rote-beete",
        "description": null,
        "priority": 0,
        "iconLink": "https://d3hvwccx09j84u.cloudfront.net/200,200/ingredient-families/58877cf3ed71a76e9c03fb50-bd433463.png",
        "usageByCountry": {
          "AT": 61,
          "AU": 54,
          "BE": 44,
          "CA": 9,
          "CH": 4,
          "DE": 50,
          "ER": 0,
          "FR": 6,
          "GB": 19,
          "LU": 45,
          "NL": 46,
          "NZ": 27,
          "ML": 1,
          "US": 9
        },
        "createdAt": "2017-01-24T16:12:35+00:00",
        "updatedAt": "2017-01-24T16:12:35+00:00"
      }
    },
    {
      "country": "DE",
      "id": "554b2645fd2cb983608b4567",
      "type": "frischer oregano",
      "name": "frischer Oregano",
      "slug": "frischer-oregano",
      "description": null,
      "internalName": null,
      "shipped": true,
      "imageLink": "https://d3hvwccx09j84u.cloudfront.net/200,200/image/554b2645fd2cb983608b4567.png",
      "usage": 120,
      "hasDuplicatedName": null,
      "allergens": [],
      "family": {
        "id": "58877cf3ed71a76e9c03fbf0",
        "type": "oregano",
        "name": "Oregano",
        "slug": "oregano",
        "description": null,
        "priority": 0,
        "iconLink": "https://d3hvwccx09j84u.cloudfront.net/200,200/ingredient-families/58877cf3ed71a76e9c03fbf0-6e86fa56.png",
        "usageByCountry": {
          "AT": 189,
          "AU": 88,
          "BE": 199,
          "CA": 43,
          "CH": 36,
          "DE": 166,
          "ER": 6,
          "FR": 31,
          "GB": 89,
          "LU": 160,
          "NL": 225,
          "NZ": 24,
          "ML": 0,
          "US": 155
        },
        "createdAt": "2017-01-24T16:12:35+00:00",
        "updatedAt": "2017-01-24T16:12:35+00:00"
      }
    },
    {
      "country": "DE",
      "id": "5566ebf34dab71e6078b456b",
      "type": "salatherz",
      "name": "Salatherz",
      "slug": "salatherz",
      "description": null,
      "internalName": null,
      "shipped": true,
      "imageLink": "https://d3hvwccx09j84u.cloudfront.net/200,200/image/5566ebf34dab71e6078b456b.png",
      "usage": 256,
      "hasDuplicatedName": null,
      "allergens": [],
      "family": {
        "id": "58877cf3ed71a76e9c03fc22",
        "type": "salad",
        "name": "Salat",
        "slug": "salat",
        "description": null,
        "priority": 0,
        "iconLink": "https://d3hvwccx09j84u.cloudfront.net/200,200/ingredient-families/58877cf3ed71a76e9c03fc22-d5b9cc88.png",
        "usageByCountry": {
          "AT": 933,
          "AU": 445,
          "BE": 460,
          "CA": 159,
          "CH": 198,
          "DE": 850,
          "ER": 5,
          "FR": 99,
          "GB": 392,
          "LU": 472,
          "NL": 542,
          "NZ": 127,
          "ML": 0,
          "US": 393
        },
        "createdAt": "2017-01-24T16:12:35+00:00",
        "updatedAt": "2017-01-24T16:12:35+00:00"
      }
    },
    {
      "country": "DE",
      "id": "554b21b64dab71a6058b4572",
      "type": "cheddar",
      "name": "geriebener Cheddar",
      "slug": "geriebener-cheddar",
      "description": null,
      "internalName": "geriebener Cheddar",
      "shipped": true,
      "imageLink": "https://d3hvwccx09j84u.cloudfront.net/200,200/image/554b21b64dab71a6058b4572.png",
      "usage": 110,
      "hasDuplicatedName": null,
      "allergens": [
        {
          "id": "57962a07b7e8697d4b3052fa",
          "type": "milk",
          "name": "Milch",
          "slug": "laktose",
          "description": null,
          "tracesOf": false,
          "triggersTracesOf": false,
          "iconLink": "https://d3hvwccx09j84u.cloudfront.net/0,0/allergens/57962a07b7e8697d4b3052fa-be127d3f.png",
          "usage": 1018
        }
      ],
      "family": {
        "id": "58877cf3ed71a76e9c03fb68",
        "type": "cheese",
        "name": "Greyerzer",
        "slug": "greyerzer",
        "description": null,
        "priority": 0,
        "iconLink": "https://d3hvwccx09j84u.cloudfront.net/200,200/ingredient-families/58877cf3ed71a76e9c03fb68-b56fbaaf.png",
        "usageByCountry": {
          "AT": 1889,
          "AU": 708,
          "BE": 959,
          "CA": 367,
          "CH": 331,
          "DE": 1778,
          "ER": 91,
          "FR": 267,
          "GB": 876,
          "LU": 1325,
          "NL": 1163,
          "NZ": 169,
          "ML": 648,
          "US": 1675
        },
        "createdAt": "2017-01-24T16:12:35+00:00",
        "updatedAt": "2017-01-24T16:12:35+00:00"
      }
    },
    {
      "country": "DE",
      "id": "5804d8e4cc7bd0349c3f9792",
      "type": "burgerbrotchen",
      "name": "Burgerbrötchen",
      "slug": "burgerbrotchen",
      "description": null,
      "internalName": null,
      "shipped": true,
      "imageLink": "https://d3hvwccx09j84u.cloudfront.net/200,200/image/5804d8e4cc7bd0349c3f9791-0bfbb31e.png",
      "usage": 93,
      "hasDuplicatedName": null,
      "allergens": [
        {
          "id": "57962a07b7e8697d4b3052f5",
          "type": "gluten",
          "name": "Weizen",
          "slug": "weizen",
          "description": null,
          "tracesOf": false,
          "triggersTracesOf": false,
          "iconLink": "https://d3hvwccx09j84u.cloudfront.net/0,0/allergens/57962a07b7e8697d4b3052f5-e20d9ca4.png",
          "usage": 1406
        },
        {
          "id": "57962a07b7e8697d4b3052fe",
          "type": "sesame",
          "name": "Sesam",
          "slug": "sesam",
          "description": null,
          "tracesOf": false,
          "triggersTracesOf": false,
          "iconLink": "https://d3hvwccx09j84u.cloudfront.net/0,0/allergens/57962a07b7e8697d4b3052fe-feb8e168.png",
          "usage": 175
        }
      ],
      "family": {
        "id": "58877cf3ed71a76e9c03fb54",
        "type": "bread",
        "name": "Brot",
        "slug": "brot",
        "description": null,
        "priority": 0,
        "iconLink": "https://d3hvwccx09j84u.cloudfront.net/200,200/ingredient-families/58877cf3ed71a76e9c03fb54-1e82dfa9.png",
        "usageByCountry": {
          "AT": 713,
          "AU": 371,
          "BE": 426,
          "CA": 175,
          "CH": 131,
          "DE": 651,
          "ER": 50,
          "FR": 118,
          "GB": 330,
          "LU": 588,
          "NL": 514,
          "NZ": 111,
          "ML": 181,
          "US": 755
        },
        "createdAt": "2017-01-24T16:12:35+00:00",
        "updatedAt": "2017-01-24T16:12:35+00:00"
      }
    },
    {
      "country": "DE",
      "id": "554b1f134dab71aa058b456e",
      "type": "crème fraîche",
      "name": "Crème fraîche",
      "slug": "creme-fraiche",
      "description": null,
      "internalName": null,
      "shipped": true,
      "imageLink": "https://d3hvwccx09j84u.cloudfront.net/200,200/image/554b1f134dab71aa058b456e.png",
      "usage": 305,
      "hasDuplicatedName": null,
      "allergens": [
        {
          "id": "57962a07b7e8697d4b3052fa",
          "type": "milk",
          "name": "Milch",
          "slug": "laktose",
          "description": null,
          "tracesOf": false,
          "triggersTracesOf": false,
          "iconLink": "https://d3hvwccx09j84u.cloudfront.net/0,0/allergens/57962a07b7e8697d4b3052fa-be127d3f.png",
          "usage": 1018
        }
      ],
      "family": {
        "id": "58877cf3ed71a76e9c03fb86",
        "type": "creme-fraiche",
        "name": "Crème Fraîche",
        "slug": "creme-fraiche",
        "description": null,
        "priority": 0,
        "iconLink": "https://d3hvwccx09j84u.cloudfront.net/200,200/ingredient-families/58877cf3ed71a76e9c03fb86-533fc64c.png",
        "usageByCountry": {
          "AT": 321,
          "AU": 0,
          "BE": 119,
          "CA": 0,
          "CH": 81,
          "DE": 305,
          "ER": 0,
          "FR": 21,
          "GB": 328,
          "LU": 127,
          "NL": 144,
          "NZ": 0,
          "ML": 0,
          "US": 0
        },
        "createdAt": "2017-01-24T16:12:35+00:00",
        "updatedAt": "2017-01-24T16:12:35+00:00"
      }
    },
    {
      "country": "DE",
      "id": "554b22cb4dab71c8058b4570",
      "type": "olivenol",
      "name": "Olivenöl*",
      "slug": "olivenol",
      "description": null,
      "internalName": null,
      "shipped": false,
      "imageLink": "https://d3hvwccx09j84u.cloudfront.net/200,200/image/554b22cb4dab71c8058b4570.png",
      "usage": 1250,
      "hasDuplicatedName": null,
      "allergens": [],
      "family": {
        "id": "58877cf3ed71a76e9c03fbe8",
        "type": "oil",
        "name": "Öl",
        "slug": "ol",
        "description": null,
        "priority": 0,
        "iconLink": "https://d3hvwccx09j84u.cloudfront.net/200,200/ingredient-families/58877cf3ed71a76e9c03fbe8-34c502d3.png",
        "usageByCountry": {
          "AT": 3004,
          "AU": 136,
          "BE": 433,
          "CA": 940,
          "CH": 624,
          "DE": 2780,
          "ER": 171,
          "FR": 109,
          "GB": 4,
          "LU": 555,
          "NL": 503,
          "NZ": 0,
          "ML": 32,
          "US": 978
        },
        "createdAt": "2017-01-24T16:12:35+00:00",
        "updatedAt": "2017-01-24T16:12:35+00:00"
      }
    },
    {
      "country": "DE",
      "id": "554b1c284dab71a9058b456b",
      "type": "salz",
      "name": "Salz*",
      "slug": "salz",
      "description": null,
      "internalName": null,
      "shipped": false,
      "imageLink": "https://d3hvwccx09j84u.cloudfront.net/200,200/image/554b1c284dab71a9058b456b.png",
      "usage": 3019,
      "hasDuplicatedName": null,
      "allergens": [],
      "family": {
        "id": "58877cf3ed71a76e9c03fc25",
        "type": "salt",
        "name": "Salz",
        "slug": "salz",
        "description": null,
        "priority": 0,
        "iconLink": "https://d3hvwccx09j84u.cloudfront.net/200,200/ingredient-families/58877cf3ed71a76e9c03fc25-abd39ad0.png",
        "usageByCountry": {
          "AT": 3264,
          "AU": 471,
          "BE": 51,
          "CA": 261,
          "CH": 645,
          "DE": 3024,
          "ER": 178,
          "FR": 2,
          "GB": 122,
          "LU": 31,
          "NL": 66,
          "NZ": 241,
          "ML": 65,
          "US": 2638
        },
        "createdAt": "2017-01-24T16:12:35+00:00",
        "updatedAt": "2017-01-24T16:12:35+00:00"
      }
    },
    {
      "country": "DE",
      "id": "554b1c56fd2cb99c598b4573",
      "type": "pfefferkörner",
      "name": "Pfefferkörner",
      "slug": "pfefferkorner",
      "description": null,
      "internalName": null,
      "shipped": false,
      "imageLink": "https://d3hvwccx09j84u.cloudfront.net/200,200/image/554b1c56fd2cb99c598b4573.png",
      "usage": 190,
      "hasDuplicatedName": null,
      "allergens": [],
      "family": {
        "id": "58877cf3ed71a76e9c03fc05",
        "type": "pepper-spice",
        "name": "Pfeffer (Gewürz)",
        "slug": "pfeffer-gewurz",
        "description": null,
        "priority": 0,
        "iconLink": "https://d3hvwccx09j84u.cloudfront.net/200,200/ingredient-families/58877cf3ed71a76e9c03fc05-00a37cd9.png",
        "usageByCountry": {
          "AT": 3237,
          "AU": 122,
          "BE": 12,
          "CA": 142,
          "CH": 628,
          "DE": 3006,
          "ER": 181,
          "FR": 4,
          "GB": 158,
          "LU": 18,
          "NL": 17,
          "NZ": 7,
          "ML": 71,
          "US": 2674
        },
        "createdAt": "2017-01-24T16:12:35+00:00",
        "updatedAt": "2017-01-24T16:12:35+00:00"
      }
    },
    {
      "country": "DE",
      "id": "554b2319fd2cb9ba598b456d",
      "type": "zucker",
      "name": "Zucker*",
      "slug": "zucker",
      "description": null,
      "internalName": "Zucker [home]",
      "shipped": false,
      "imageLink": "https://d3hvwccx09j84u.cloudfront.net/200,200/image/554b2319fd2cb9ba598b456d.png",
      "usage": 842,
      "hasDuplicatedName": null,
      "allergens": [],
      "family": {
        "id": "58877cf3ed71a76e9c03fc3b",
        "type": "sugar",
        "name": "Zucker",
        "slug": "zucker",
        "description": null,
        "priority": 0,
        "iconLink": "https://d3hvwccx09j84u.cloudfront.net/200,200/ingredient-families/58877cf3ed71a76e9c03fc3b-20b617ed.png",
        "usageByCountry": {
          "AT": 956,
          "AU": 351,
          "BE": 205,
          "CA": 264,
          "CH": 163,
          "DE": 868,
          "ER": 0,
          "FR": 50,
          "GB": 59,
          "LU": 172,
          "NL": 242,
          "NZ": 138,
          "ML": 0,
          "US": 26
        },
        "createdAt": "2017-01-24T16:12:35+00:00",
        "updatedAt": "2017-01-24T16:12:35+00:00"
      }
    },
    {
      "country": "DE",
      "id": "554b1bf6f8b25eef3e8b4570",
      "type": "ol",
      "name": "Öl*",
      "slug": "ol",
      "description": null,
      "internalName": null,
      "shipped": false,
      "imageLink": "https://d3hvwccx09j84u.cloudfront.net/200,200/image/554b1bf6f8b25eef3e8b4570.png",
      "usage": 1499,
      "hasDuplicatedName": null,
      "allergens": [],
      "family": {
        "id": "58877cf3ed71a76e9c03fbe8",
        "type": "oil",
        "name": "Öl",
        "slug": "ol",
        "description": null,
        "priority": 0,
        "iconLink": "https://d3hvwccx09j84u.cloudfront.net/200,200/ingredient-families/58877cf3ed71a76e9c03fbe8-34c502d3.png",
        "usageByCountry": {
          "AT": 3004,
          "AU": 136,
          "BE": 433,
          "CA": 940,
          "CH": 624,
          "DE": 2780,
          "ER": 171,
          "FR": 109,
          "GB": 4,
          "LU": 555,
          "NL": 503,
          "NZ": 0,
          "ML": 32,
          "US": 978
        },
        "createdAt": "2017-01-24T16:12:35+00:00",
        "updatedAt": "2017-01-24T16:12:35+00:00"
      }
    }
  ],
  "allergens": [
    {
      "id": "57962a07b7e8697d4b3052fa",
      "type": "milk",
      "name": "Milch",
      "slug": "laktose",
      "description": null,
      "tracesOf": false,
      "triggersTracesOf": false,
      "iconLink": "https://d3hvwccx09j84u.cloudfront.net/0,0/allergens/57962a07b7e8697d4b3052fa-be127d3f.png",
      "usage": 1018
    },
    {
      "id": "57962a07b7e8697d4b3052f5",
      "type": "gluten",
      "name": "Weizen",
      "slug": "weizen",
      "description": null,
      "tracesOf": false,
      "triggersTracesOf": false,
      "iconLink": "https://d3hvwccx09j84u.cloudfront.net/0,0/allergens/57962a07b7e8697d4b3052f5-e20d9ca4.png",
      "usage": 1406
    },
    {
      "id": "57962a07b7e8697d4b3052fe",
      "type": "sesame",
      "name": "Sesam",
      "slug": "sesam",
      "description": null,
      "tracesOf": false,
      "triggersTracesOf": false,
      "iconLink": "https://d3hvwccx09j84u.cloudfront.net/0,0/allergens/57962a07b7e8697d4b3052fe-feb8e168.png",
      "usage": 175
    }
  ],
  "utensils": [
    {
      "id": "57e2674fb7e8697d4b305374",
      "type": "stove",
      "name": "Ofen"
    },
    {
      "id": "57e2674fb7e8697d4b305375",
      "type": "pan",
      "name": "Pfanne"
    }
  ],
  "tags": [
    {
      "id": "57d13370b7e8697d4b305317",
      "type": "vegetarian",
      "name": "Vegetarisch",
      "slug": "vegetarisch",
      "iconLink": "https://d3hvwccx09j84u.cloudfront.net/200,200/tags/icon-veggie%403x.png",
      "numberOfRecipes": 7556,
      "numberOfRecipesByCountry": {
        "AT": 1623,
        "AU": 346,
        "BE": 752,
        "CA": 165,
        "CH": 258,
        "DE": 1507,
        "ER": 0,
        "FR": 207,
        "GB": 368,
        "LU": 1011,
        "NL": 893,
        "NZ": 10,
        "ML": 61,
        "US": 355
      }
    }
  ],
  "cuisines": [
    {
      "id": "57ebbc17b7e8697d4b3053a4",
      "type": "american",
      "name": "Amerikanisch",
      "slug": "amerikanisch",
      "iconLink": "https://d3hvwccx09j84u.cloudfront.net/0,0/cuisines/57ebbc17b7e8697d4b3053a4-aafc03e6.jpg",
      "usage": 3895
    }
  ],
  "wines": [],
  "marketplaceItems": [],
  "author": null,
  "label": null,
  "yieldType": "servings",
  "yields": [
    {
      "yields": 2,
      "ingredients": [
        {
          "id": "554b25fcfd2cb973608b4567",
          "amount": 600,
          "unit": "g"
        },
        {
          "id": "556d72274dab712c498b4568",
          "amount": 1,
          "unit": "g"
        },
        {
          "id": "55798feb4dab71e4468b4568",
          "amount": 2,
          "unit": "Stück"
        },
        {
          "id": "555357a3f8b25e89038b456a",
          "amount": 0.5,
          "unit": "Stück"
        },
        {
          "id": "554b2abcf8b25eef3e8b4573",
          "amount": 1,
          "unit": "Stück"
        },
        {
          "id": "555dbfadf8b25e246a8b4569",
          "amount": 1,
          "unit": "Stück"
        },
        {
          "id": "554b2645fd2cb983608b4567",
          "amount": 5,
          "unit": "g"
        },
        {
          "id": "5566ebf34dab71e6078b456b",
          "amount": 1,
          "unit": "g"
        },
        {
          "id": "554b21b64dab71a6058b4572",
          "amount": 50,
          "unit": "g"
        },
        {
          "id": "5804d8e4cc7bd0349c3f9792",
          "amount": 2,
          "unit": "Stück"
        },
        {
          "id": "554b1f134dab71aa058b456e",
          "amount": 75,
          "unit": "g"
        },
        {
          "id": "554b22cb4dab71c8058b4570",
          "amount": null,
          "unit": "Einheit"
        },
        {
          "id": "554b1c284dab71a9058b456b",
          "amount": null,
          "unit": "Einheit"
        },
        {
          "id": "554b1c56fd2cb99c598b4573",
          "amount": null,
          "unit": "Einheit"
        },
        {
          "id": "554b2319fd2cb9ba598b456d",
          "amount": null,
          "unit": "Einheit"
        },
        {
          "id": "554b1bf6f8b25eef3e8b4570",
          "amount": null,
          "unit": "Einheit"
        }
      ]
    },
    {
      "yields": 4,
      "ingredients": [
        {
          "id": "554b25fcfd2cb973608b4567",
          "amount": 1200,
          "unit": "g"
        },
        {
          "id": "556d72274dab712c498b4568",
          "amount": 2,
          "unit": "g"
        },
        {
          "id": "55798feb4dab71e4468b4568",
          "amount": 4,
          "unit": "Stück"
        },
        {
          "id": "555357a3f8b25e89038b456a",
          "amount": 1,
          "unit": "Stück"
        },
        {
          "id": "554b2abcf8b25eef3e8b4573",
          "amount": 2,
          "unit": "Stück"
        },
        {
          "id": "555dbfadf8b25e246a8b4569",
          "amount": 2,
          "unit": "Stück"
        },
        {
          "id": "554b2645fd2cb983608b4567",
          "amount": 10,
          "unit": "g"
        },
        {
          "id": "5566ebf34dab71e6078b456b",
          "amount": 2,
          "unit": "g"
        },
        {
          "id": "554b21b64dab71a6058b4572",
          "amount": 100,
          "unit": "g"
        },
        {
          "id": "5804d8e4cc7bd0349c3f9792",
          "amount": 4,
          "unit": "Stück"
        },
        {
          "id": "554b1f134dab71aa058b456e",
          "amount": 150,
          "unit": "g"
        },
        {
          "id": "554b22cb4dab71c8058b4570",
          "amount": null,
          "unit": "Einheit"
        },
        {
          "id": "554b1c284dab71a9058b456b",
          "amount": null,
          "unit": "Einheit"
        },
        {
          "id": "554b1c56fd2cb99c598b4573",
          "amount": null,
          "unit": "Einheit"
        },
        {
          "id": "554b2319fd2cb9ba598b456d",
          "amount": null,
          "unit": "Einheit"
        },
        {
          "id": "554b1bf6f8b25eef3e8b4570",
          "amount": null,
          "unit": "Einheit"
        }
      ]
    }
  ],
  "steps": [
    {
      "index": 1,
      "instructionsMarkdown": "Backofen auf 200 °C Ober-/Unterhitze vorheizen. Kartoffeln schälen und in ca. 1 cm dicke Pommes schneiden. Diese in einer Schüssel mit 2 EL Olivenöl, Paprikapulver, Salz und Pfeffer vermischen und auf einem mit Backpapier belegten Backblech verteilen. Ein wenig Platz für die Portobello-Pilze lassen. In den Ofen schieben und ca. 20 Min. garen. Nach 10 Min., oder wenn die Burgerbrötchen zum Aufbacken in den Ofen kommen, einmal wenden.",
      "instructionsHTML": "<p>Backofen auf 200 °C Ober-/Unterhitze vorheizen. Kartoffeln schälen und in ca. 1 cm dicke Pommes schneiden. Diese in einer Schüssel mit 2 EL Olivenöl, Paprikapulver, Salz und Pfeffer vermischen und auf einem mit Backpapier belegten Backblech verteilen. Ein wenig Platz für die Portobello-Pilze lassen. In den Ofen schieben und ca. 20 Min. garen. Nach 10 Min., oder wenn die Burgerbrötchen zum Aufbacken in den Ofen kommen, einmal wenden.</p>",
      "instructions": "Backofen auf 200 °C Ober-/Unterhitze vorheizen. Kartoffeln schälen und in ca. 1 cm dicke Pommes schneiden. Diese in einer Schüssel mit 2 EL Olivenöl, Paprikapulver, Salz und Pfeffer vermischen und auf einem mit Backpapier belegten Backblech verteilen. Ein wenig Platz für die Portobello-Pilze lassen. In den Ofen schieben und ca. 20 Min. garen. Nach 10 Min., oder wenn die Burgerbrötchen zum Aufbacken in den Ofen kommen, einmal wenden.",
      "timers": [
        {
          "name": "Backofen vorheizen",
          "duration": "PT20M",
          "temperature": 200,
          "temperatureUnit": "C",
          "ovenMode": "PreHeating"
        },
        {
          "name": "Kartoffeln garen",
          "duration": "PT20M",
          "temperature": 200,
          "temperatureUnit": "C",
          "ovenMode": "TopBottomHeating"
        },
        {
          "name": "Kartoffeln wenden und Burgerbrötchen aufbacken",
          "duration": "PT10M",
          "temperature": null,
          "temperatureUnit": null,
          "ovenMode": null
        }
      ],
      "images": [
        {
          "link": "https://d3hvwccx09j84u.cloudfront.net/0,0/5576d5674dab71fc2f8b4568/step_5584379194f61.jpg",
          "caption": "Kartoffeln auf Backblech"
        }
      ],
      "videos": [],
      "ingredients": [
        "554b25fcfd2cb973608b4567",
        "556d72274dab712c498b4568",
        "55798feb4dab71e4468b4568",
        "554b22cb4dab71c8058b4570",
        "554b1c284dab71a9058b456b",
        "554b1c56fd2cb99c598b4573"
      ],
      "utensils": [
        "57e2674fb7e8697d4b305374"
      ]
    },
    {
      "index": 2,
      "instructionsMarkdown": "Zwiebeln abziehen, halbieren und in feine Streifen schneiden. Rote Bete in dünne Scheiben schneiden. Oregano waschen und trockenschütteln, dann die Blätter fein schneiden. Äußere Blätter vom Salatherz entfernen, vom Strunk 1 cm abschneiden, Blätter waschen und abtropfen lassen. Burgerbrötchen nach Packungsanleitung im Ofen aufbacken.",
      "instructionsHTML": "<p>Zwiebeln abziehen, halbieren und in feine Streifen schneiden. Rote Bete in dünne Scheiben schneiden. Oregano waschen und trockenschütteln, dann die Blätter fein schneiden. Äußere Blätter vom Salatherz entfernen, vom Strunk 1 cm abschneiden, Blätter waschen und abtropfen lassen. Burgerbrötchen nach Packungsanleitung im Ofen aufbacken.</p>",
      "instructions": "Zwiebeln abziehen, halbieren und in feine Streifen schneiden. Rote Bete in dünne Scheiben schneiden. Oregano waschen und trockenschütteln, dann die Blätter fein schneiden. Äußere Blätter vom Salatherz entfernen, vom Strunk 1 cm abschneiden, Blätter waschen und abtropfen lassen. Burgerbrötchen nach Packungsanleitung im Ofen aufbacken.",
      "timers": [],
      "images": [
        {
          "link": "https://d3hvwccx09j84u.cloudfront.net/0,0/5576d5674dab71fc2f8b4568/step_558436287b639.jpg",
          "caption": "Oregano hacken"
        }
      ],
      "videos": [],
      "ingredients": [
        "554b2abcf8b25eef3e8b4573",
        "555dbfadf8b25e246a8b4569",
        "554b2645fd2cb983608b4567",
        "5566ebf34dab71e6078b456b",
        "5804d8e4cc7bd0349c3f9792"
      ],
      "utensils": []
    },
    {
      "index": 3,
      "instructionsMarkdown": "Limette entsaften. Portobello-Pilze säubern, Stiele evtl. vorsichtig herausbrechen. Die Pilze mit etwas Limettensaft und von allen Seiten mit Olivenöl bestreichen und mit Salz und Pfeffer bestreuen. Jeden Pilz mit ein wenig Cheddar füllen und mit der Öffnung nach oben für ca. 5–10 Min. in den Ofen neben die Kartoffeln setzen.",
      "instructionsHTML": "<p>Limette entsaften. Portobello-Pilze säubern, Stiele evtl. vorsichtig herausbrechen. Die Pilze mit etwas Limettensaft und von allen Seiten mit Olivenöl bestreichen und mit Salz und Pfeffer bestreuen. Jeden Pilz mit ein wenig Cheddar füllen und mit der Öffnung nach oben für ca. 5–10 Min. in den Ofen neben die Kartoffeln setzen.</p>",
      "instructions": "Limette entsaften. Portobello-Pilze säubern, Stiele evtl. vorsichtig herausbrechen. Die Pilze mit etwas Limettensaft und von allen Seiten mit Olivenöl bestreichen und mit Salz und Pfeffer bestreuen. Jeden Pilz mit ein wenig Cheddar füllen und mit der Öffnung nach oben für ca. 5–10 Min. in den Ofen neben die Kartoffeln setzen.",
      "timers": [
        {
          "name": "Portobello im Ofen",
          "duration": "PT10M",
          "temperature": null,
          "temperatureUnit": null,
          "ovenMode": null
        }
      ],
      "images": [
        {
          "link": "https://d3hvwccx09j84u.cloudfront.net/0,0/5576d5674dab71fc2f8b4568/step_5584375c4a972.jpg",
          "caption": "Pilze mit Käse füllen"
        }
      ],
      "videos": [],
      "ingredients": [
        "55798feb4dab71e4468b4568",
        "555357a3f8b25e89038b456a",
        "554b21b64dab71a6058b4572",
        "554b1c284dab71a9058b456b",
        "554b1c56fd2cb99c598b4573"
      ],
      "utensils": []
    },
    {
      "index": 4,
      "instructionsMarkdown": "2 EL Öl in einer kleinen Pfanne erhitzen, Zwiebeln zugeben und ca. 10 Min. bei mittlerer Hitze anbraten. 1 TL Zucker dazugeben und mit Salz und Pfeffer abschmecken. In einer kleinen Schüssel Crème fraîche mit etwas Salz und Pfeffer abschmecken und Oregano untermischen.",
      "instructionsHTML": "<p>2 EL Öl in einer kleinen Pfanne erhitzen, Zwiebeln zugeben und ca. 10 Min. bei mittlerer Hitze anbraten. 1 TL Zucker dazugeben und mit Salz und Pfeffer abschmecken. In einer kleinen Schüssel Crème fraîche mit etwas Salz und Pfeffer abschmecken und Oregano untermischen.</p>",
      "instructions": "2 EL Öl in einer kleinen Pfanne erhitzen, Zwiebeln zugeben und ca. 10 Min. bei mittlerer Hitze anbraten. 1 TL Zucker dazugeben und mit Salz und Pfeffer abschmecken. In einer kleinen Schüssel Crème fraîche mit etwas Salz und Pfeffer abschmecken und Oregano untermischen.",
      "timers": [
        {
          "name": "Zwiebeln dünsten",
          "duration": "PT10M",
          "temperature": null,
          "temperatureUnit": null,
          "ovenMode": null
        }
      ],
      "images": [],
      "videos": [],
      "ingredients": [
        "554b2abcf8b25eef3e8b4573",
        "554b2645fd2cb983608b4567",
        "554b1c284dab71a9058b456b",
        "554b1c56fd2cb99c598b4573",
        "554b2319fd2cb9ba598b456d",
        "554b1bf6f8b25eef3e8b4570",
        "554b1f134dab71aa058b456e"
      ],
      "utensils": [
        "57e2674fb7e8697d4b305375"
      ]
    },
    {
      "index": 5,
      "instructionsMarkdown": "Burgerbrötchen nach der Aufbackzeit aus dem Ofen nehmen und halbieren. Auf jeder Hälfte mit ein wenig Crème fraîche bestreichen. Dann auf der Unterseite Salatblätter, gefüllte Portobello-Pilze und Zwiebelade verteilen. Auf die Oberseite Rote Bete-Scheiben legen, mit Salz und Pfeffer würzen. Beide Hälften zusammenklappen und vorsichtig zusammendrücken. Portobello-Pilz-Burger mit den Ofen-Pommes auf Tellern verteilen, mit restlichem Crème fraîche-Dip genießen.",
      "instructionsHTML": "<p>Burgerbrötchen nach der Aufbackzeit aus dem Ofen nehmen und halbieren. Auf jeder Hälfte mit ein wenig Crème fraîche bestreichen. Dann auf der Unterseite Salatblätter, gefüllte Portobello-Pilze und Zwiebelade verteilen. Auf die Oberseite Rote Bete-Scheiben legen, mit Salz und Pfeffer würzen. Beide Hälften zusammenklappen und vorsichtig zusammendrücken. Portobello-Pilz-Burger mit den Ofen-Pommes auf Tellern verteilen, mit restlichem Crème fraîche-Dip genießen.</p>",
      "instructions": "Burgerbrötchen nach der Aufbackzeit aus dem Ofen nehmen und halbieren. Auf jeder Hälfte mit ein wenig Crème fraîche bestreichen. Dann auf der Unterseite Salatblätter, gefüllte Portobello-Pilze und Zwiebelade verteilen. Auf die Oberseite Rote Bete-Scheiben legen, mit Salz und Pfeffer würzen. Beide Hälften zusammenklappen und vorsichtig zusammendrücken. Portobello-Pilz-Burger mit den Ofen-Pommes auf Tellern verteilen, mit restlichem Crème fraîche-Dip genießen.",
      "timers": [],
      "images": [
        {
          "link": "https://d3hvwccx09j84u.cloudfront.net/0,0/5576d5674dab71fc2f8b4568/step_5584375c6d7fb.jpg",
          "caption": "Brötchen belegen"
        }
      ],
      "videos": [],
      "ingredients": [],
      "utensils": []
    }
  ],
  "averageRating": 3.4,
  "ratingsCount": 698,
  "favoritesCount": 574,
  "active": true,
  "highlighted": true,
  "isDinnerToLunch": false,
  "isExcludedFromIndex": false,
  "isPremium": false,
  "websiteUrl": "https://www.hellofresh.de/recipes/herzhaft-gefullte-portobello-pilz-burger-mit-ofen-pommes-5576d5674dab71fc2f8b4568",
  "clonedFrom": null,
  "canonical": null,
  "canonicalLink": null
}
