{
  "country": "DE",
  "id": "57567d31f8b25e48148b4568",
  "name": "Pikant glasierte Putenbrust mit Ofen-Möhren",
  "seoName": null,
  "category": null,
  "slug": "pikant-glasierte-putenbrust-mit-ofen-mohren",
  "headline": "Cashewkernen und fluffigem Basmatireis",
  "description": "Cashewkerne gehören rein botanisch gesehen eigentlich zum Steinobst. Die kleinen Kra\u001fftpakete bieten massig Magnesium und Eiweiß bei einem recht geringen Fettgehalt. Perfekt also um Dir die pikante Putenbrust, das Ofengemüse und den flu\u001effigen Basmatireis zu verfeinern. Guten Appetit!",
  "descriptionHTML": "<p>Cashewkerne gehören rein botanisch gesehen eigentlich zum Steinobst. Die kleinen Kra\u001fftpakete bieten massig Magnesium und Eiweiß bei einem recht geringen Fettgehalt. Perfekt also um Dir die pikante Putenbrust, das Ofengemüse und den flu\u001effigen Basmatireis zu verfeinern. Guten Appetit!</p>",
  "descriptionMarkdown": "Cashewkerne gehören rein botanisch gesehen eigentlich zum Steinobst. Die kleinen Kra\u001fftpakete bieten massig Magnesium und Eiweiß bei einem recht geringen Fettgehalt. Perfekt also um Dir die pikante Putenbrust, das Ofengemüse und den flu\u001effigen Basmatireis zu verfeinern. Guten Appetit!",
  "seoDescription": null,
  "comment": null,
  "difficulty": 2,
  "prepTime": "PT45M",
  "totalTime": null,
  "servingSize": 0,
  "createdAt": "2016-06-07T07:52:16+00:00",
  "updatedAt": "2017-04-25T11:34:02+00:00",
  "link": "https://hellofresh.com/recipes/57567d31f8b25e48148b4568",
  "imageLink": "https://d3hvwccx09j84u.cloudfront.net/0,0/image/pikant-glasierte-putenbrust-mit-ofen-mohren-8828e966.jpg",
  "cardLink": "https://ddw4dkk7s1lkt.cloudfront.nethttps://ddw4dkk7s1lkt.cloudfront.net/card/pikant-glasierte-putenbrust-mit-ofen-mohren-9726cf5e.pdf?t=20160706155530",
  "videoLink": null,
  "nutrition": [
    {
      "type": "57b42a48b7e8697d4b30530d",
      "name": "Energie (kJ)",
      "amount": 2736,
      "unit": "kJ"
    },
    {
      "type": "57b42a48b7e8697d4b305304",
      "name": "Energie (kcal)",
      "amount": 654,
      "unit": "kcal"
    },
    {
      "type": "57b42a48b7e8697d4b305307",
      "name": "Fett",
      "amount": 19,
      "unit": "g"
    },
    {
      "type": "57b42a48b7e8697d4b305308",
      "name": "davon gesättigte Fettsäuren",
      "amount": 0,
      "unit": "g"
    },
    {
      "type": "57b42a48b7e8697d4b305305",
      "name": "Kohlenhydrate",
      "amount": 88,
      "unit": "g"
    },
    {
      "type": "57b42a48b7e8697d4b305306",
      "name": "davon Zucker",
      "amount": 0,
      "unit": "g"
    },
    {
      "type": "57b42a48b7e8697d4b30530a",
      "name": "Ballaststoffe",
      "amount": 5,
      "unit": "g"
    },
    {
      "type": "57b42a48b7e8697d4b305309",
      "name": "Eiweiß",
      "amount": 32,
      "unit": "g"
    },
    {
      "type": "57b42a48b7e8697d4b30530c",
      "name": "Cholesterol",
      "amount": 0,
      "unit": "mg"
    },
    {
      "type": "57b42a48b7e8697d4b30530b",
      "name": "Salz",
      "amount": 0,
      "unit": "g"
    }
  ],
  "ingredients": [
    {
      "country": "DE",
      "id": "554b23dff8b25ef53e8b456f",
      "type": "karotten",
      "name": "Karotte",
      "slug": "karotten",
      "description": null,
      "internalName": null,
      "shipped": true,
      "imageLink": "https://d3hvwccx09j84u.cloudfront.net/200,200/image/554b23dff8b25ef53e8b456f.png",
      "usage": 566,
      "hasDuplicatedName": null,
      "allergens": [],
      "family": {
        "id": "58877cf3ed71a76e9c03fb62",
        "type": "carrot",
        "name": "Karotte",
        "slug": "karotte",
        "description": null,
        "priority": 0,
        "iconLink": "https://d3hvwccx09j84u.cloudfront.net/200,200/ingredient-families/58877cf3ed71a76e9c03fb62-c4a1f62d.png",
        "usageByCountry": {
          "AT": 679,
          "AU": 553,
          "BE": 225,
          "CA": 127,
          "CH": 130,
          "DE": 627,
          "ER": 27,
          "FR": 49,
          "GB": 343,
          "LU": 220,
          "NL": 263,
          "NZ": 175,
          "ML": 243,
          "US": 318
        },
        "createdAt": "2017-01-24T16:12:35+00:00",
        "updatedAt": "2017-01-24T16:12:35+00:00"
      }
    },
    {
      "country": "DE",
      "id": "554b34554dab71a6058b4576",
      "type": "zwiebel",
      "name": "Zwiebel",
      "slug": "zwiebel",
      "description": null,
      "internalName": null,
      "shipped": true,
      "imageLink": "https://d3hvwccx09j84u.cloudfront.net/200,200/image/554b34554dab71a6058b4576.png",
      "usage": 783,
      "hasDuplicatedName": null,
      "allergens": [],
      "family": {
        "id": "58877cf3ed71a76e9c03fbee",
        "type": "onion",
        "name": "Zwiebel",
        "slug": "zwiebel",
        "description": null,
        "priority": 0,
        "iconLink": "https://d3hvwccx09j84u.cloudfront.net/200,200/ingredient-families/58877cf3ed71a76e9c03fbee-34de32d5.png",
        "usageByCountry": {
          "AT": 1698,
          "AU": 1175,
          "BE": 1213,
          "CA": 672,
          "CH": 321,
          "DE": 1582,
          "ER": 152,
          "FR": 334,
          "GB": 1502,
          "LU": 1592,
          "NL": 1429,
          "NZ": 274,
          "ML": 188,
          "US": 2363
        },
        "createdAt": "2017-01-24T16:12:35+00:00",
        "updatedAt": "2017-01-24T16:12:35+00:00"
      }
    },
    {
      "country": "DE",
      "id": "554b22cb4dab71c8058b4570",
      "type": "olivenol",
      "name": "Olivenöl*",
      "slug": "olivenol",
      "description": null,
      "internalName": null,
      "shipped": false,
      "imageLink": "https://d3hvwccx09j84u.cloudfront.net/200,200/image/554b22cb4dab71c8058b4570.png",
      "usage": 1250,
      "hasDuplicatedName": null,
      "allergens": [],
      "family": {
        "id": "58877cf3ed71a76e9c03fbe8",
        "type": "oil",
        "name": "Öl",
        "slug": "ol",
        "description": null,
        "priority": 0,
        "iconLink": "https://d3hvwccx09j84u.cloudfront.net/200,200/ingredient-families/58877cf3ed71a76e9c03fbe8-34c502d3.png",
        "usageByCountry": {
          "AT": 3004,
          "AU": 136,
          "BE": 433,
          "CA": 940,
          "CH": 624,
          "DE": 2780,
          "ER": 171,
          "FR": 109,
          "GB": 4,
          "LU": 555,
          "NL": 503,
          "NZ": 0,
          "ML": 32,
          "US": 978
        },
        "createdAt": "2017-01-24T16:12:35+00:00",
        "updatedAt": "2017-01-24T16:12:35+00:00"
      }
    },
    {
      "country": "DE",
      "id": "554b1c284dab71a9058b456b",
      "type": "salz",
      "name": "Salz*",
      "slug": "salz",
      "description": null,
      "internalName": null,
      "shipped": false,
      "imageLink": "https://d3hvwccx09j84u.cloudfront.net/200,200/image/554b1c284dab71a9058b456b.png",
      "usage": 3019,
      "hasDuplicatedName": null,
      "allergens": [],
      "family": {
        "id": "58877cf3ed71a76e9c03fc25",
        "type": "salt",
        "name": "Salz",
        "slug": "salz",
        "description": null,
        "priority": 0,
        "iconLink": "https://d3hvwccx09j84u.cloudfront.net/200,200/ingredient-families/58877cf3ed71a76e9c03fc25-abd39ad0.png",
        "usageByCountry": {
          "AT": 3264,
          "AU": 471,
          "BE": 51,
          "CA": 261,
          "CH": 645,
          "DE": 3024,
          "ER": 178,
          "FR": 2,
          "GB": 122,
          "LU": 31,
          "NL": 66,
          "NZ": 241,
          "ML": 65,
          "US": 2638
        },
        "createdAt": "2017-01-24T16:12:35+00:00",
        "updatedAt": "2017-01-24T16:12:35+00:00"
      }
    },
    {
      "country": "DE",
      "id": "55b0a135fd2cb9121e8b4567",
      "type": "pfeffer",
      "name": "Pfeffer*",
      "slug": "pfeffer",
      "description": null,
      "internalName": "Pfeffer [home]",
      "shipped": false,
      "imageLink": "https://d3hvwccx09j84u.cloudfront.net/200,200/image/55b0a135fd2cb9121e8b4567.png",
      "usage": 2774,
      "hasDuplicatedName": null,
      "allergens": [],
      "family": {
        "id": "58877cf3ed71a76e9c03fc05",
        "type": "pepper-spice",
        "name": "Pfeffer (Gewürz)",
        "slug": "pfeffer-gewurz",
        "description": null,
        "priority": 0,
        "iconLink": "https://d3hvwccx09j84u.cloudfront.net/200,200/ingredient-families/58877cf3ed71a76e9c03fc05-00a37cd9.png",
        "usageByCountry": {
          "AT": 3237,
          "AU": 122,
          "BE": 12,
          "CA": 142,
          "CH": 628,
          "DE": 3006,
          "ER": 181,
          "FR": 4,
          "GB": 158,
          "LU": 18,
          "NL": 17,
          "NZ": 7,
          "ML": 71,
          "US": 2674
        },
        "createdAt": "2017-01-24T16:12:35+00:00",
        "updatedAt": "2017-01-24T16:12:35+00:00"
      }
    },
    {
      "country": "DE",
      "id": "554b3534f8b25ef53e8b4575",
      "type": "basmatireis",
      "name": "Basmatireis",
      "slug": "basmatireis",
      "description": null,
      "internalName": null,
      "shipped": true,
      "imageLink": "https://d3hvwccx09j84u.cloudfront.net/200,200/image/554b3534f8b25ef53e8b4575.png",
      "usage": 194,
      "hasDuplicatedName": null,
      "allergens": [
        {
          "id": "57962a07b7e8697d4b3052f3",
          "type": "maycontaintracesofallergens",
          "name": "kann Spuren von Allergenen enthalten",
          "slug": "kann-spuren-von-allergenen-enthalten",
          "description": null,
          "tracesOf": false,
          "triggersTracesOf": true,
          "iconLink": null,
          "usage": 1649
        }
      ],
      "family": {
        "id": "58877cf3ed71a76e9c03fc1c",
        "type": "rice",
        "name": "Reis",
        "slug": "reis",
        "description": null,
        "priority": 0,
        "iconLink": "https://d3hvwccx09j84u.cloudfront.net/200,200/ingredient-families/58877cf3ed71a76e9c03fc1c-0b4adebd.png",
        "usageByCountry": {
          "AT": 540,
          "AU": 405,
          "BE": 265,
          "CA": 169,
          "CH": 114,
          "DE": 505,
          "ER": 39,
          "FR": 79,
          "GB": 480,
          "LU": 361,
          "NL": 319,
          "NZ": 107,
          "ML": 328,
          "US": 527
        },
        "createdAt": "2017-01-24T16:12:35+00:00",
        "updatedAt": "2017-01-24T16:12:35+00:00"
      }
    },
    {
      "country": "DE",
      "id": "554b7f33fd2cb96c628b456a",
      "type": "ingwer",
      "name": "Ingwer",
      "slug": "ingwer",
      "description": null,
      "internalName": null,
      "shipped": true,
      "imageLink": "https://d3hvwccx09j84u.cloudfront.net/200,200/image/554b7f33fd2cb96c628b456a.png",
      "usage": 241,
      "hasDuplicatedName": null,
      "allergens": [],
      "family": {
        "id": "58877cf3ed71a76e9c03fba7",
        "type": "ginger",
        "name": "Ingwer",
        "slug": "ingwer",
        "description": null,
        "priority": 0,
        "iconLink": "https://d3hvwccx09j84u.cloudfront.net/200,200/ingredient-families/58877cf3ed71a76e9c03fba7-565cc248.png",
        "usageByCountry": {
          "AT": 278,
          "AU": 225,
          "BE": 200,
          "CA": 107,
          "CH": 52,
          "DE": 241,
          "ER": 20,
          "FR": 57,
          "GB": 231,
          "LU": 241,
          "NL": 220,
          "NZ": 65,
          "ML": 25,
          "US": 246
        },
        "createdAt": "2017-01-24T16:12:35+00:00",
        "updatedAt": "2017-01-24T16:12:35+00:00"
      }
    },
    {
      "country": "DE",
      "id": "554b1adef8b25ef93e8b456a",
      "type": "rote-chili",
      "name": "roter Chili",
      "slug": "rote-chili",
      "description": null,
      "internalName": "roter Chili",
      "shipped": true,
      "imageLink": "https://d3hvwccx09j84u.cloudfront.net/200,200/image/554b1adef8b25ef93e8b456a.png",
      "usage": 325,
      "hasDuplicatedName": null,
      "allergens": [],
      "family": {
        "id": "58877cf3ed71a76e9c03fb6d",
        "type": "chili",
        "name": "Chili",
        "slug": "chili",
        "description": null,
        "priority": 0,
        "iconLink": "https://d3hvwccx09j84u.cloudfront.net/200,200/ingredient-families/58877cf3ed71a76e9c03fb6d-270fd94b.png",
        "usageByCountry": {
          "AT": 348,
          "AU": 223,
          "BE": 0,
          "CA": 48,
          "CH": 61,
          "DE": 326,
          "ER": 0,
          "FR": 0,
          "GB": 75,
          "LU": 0,
          "NL": 0,
          "NZ": 55,
          "ML": 0,
          "US": 0
        },
        "createdAt": "2017-01-24T16:12:35+00:00",
        "updatedAt": "2017-01-24T16:12:35+00:00"
      }
    },
    {
      "country": "DE",
      "id": "554b7d36fd2cb9d8608b4570",
      "type": "sojasoße",
      "name": "Sojasoße",
      "slug": "sojasosze",
      "description": null,
      "internalName": null,
      "shipped": true,
      "imageLink": "https://d3hvwccx09j84u.cloudfront.net/200,200/ingredients/554b7d36fd2cb9d8608b4570-f4ba216b.png",
      "usage": 287,
      "hasDuplicatedName": null,
      "allergens": [
        {
          "id": "57962a07b7e8697d4b3052f9",
          "type": "soya",
          "name": "Soja",
          "slug": "soja",
          "description": null,
          "tracesOf": false,
          "triggersTracesOf": false,
          "iconLink": "https://d3hvwccx09j84u.cloudfront.net/0,0/allergens/57962a07b7e8697d4b3052f9-feb8e168.png",
          "usage": 390
        },
        {
          "id": "57962a07b7e8697d4b3052f5",
          "type": "gluten",
          "name": "Weizen",
          "slug": "weizen",
          "description": null,
          "tracesOf": false,
          "triggersTracesOf": false,
          "iconLink": "https://d3hvwccx09j84u.cloudfront.net/0,0/allergens/57962a07b7e8697d4b3052f5-e20d9ca4.png",
          "usage": 1406
        }
      ],
      "family": {
        "id": "58877cf3ed71a76e9c03fc30",
        "type": "soy-sauce",
        "name": "Sojasauce",
        "slug": "sojasauce",
        "description": null,
        "priority": 0,
        "iconLink": "https://d3hvwccx09j84u.cloudfront.net/200,200/ingredient-families/58877cf3ed71a76e9c03fc30-32ed361d.png",
        "usageByCountry": {
          "AT": 343,
          "AU": 281,
          "BE": 313,
          "CA": 104,
          "CH": 80,
          "DE": 287,
          "ER": 30,
          "FR": 79,
          "GB": 283,
          "LU": 353,
          "NL": 307,
          "NZ": 116,
          "ML": 6,
          "US": 323
        },
        "createdAt": "2017-01-24T16:12:35+00:00",
        "updatedAt": "2017-01-24T16:12:35+00:00"
      }
    },
    {
      "country": "DE",
      "id": "554b7d614dab71160d8b456b",
      "type": "honig-home",
      "name": "Honig*",
      "slug": "honig",
      "description": null,
      "internalName": "Honig [home]",
      "shipped": false,
      "imageLink": "https://d3hvwccx09j84u.cloudfront.net/200,200/image/554b7d614dab71160d8b456b.png",
      "usage": 203,
      "hasDuplicatedName": null,
      "allergens": [],
      "family": {
        "id": "58877cf3ed71a76e9c03fbb3",
        "type": "honey",
        "name": "Honig",
        "slug": "honig",
        "description": null,
        "priority": 0,
        "iconLink": "https://d3hvwccx09j84u.cloudfront.net/200,200/ingredient-families/58877cf3ed71a76e9c03fbb3-efe0c124.png",
        "usageByCountry": {
          "AT": 360,
          "AU": 274,
          "BE": 368,
          "CA": 136,
          "CH": 83,
          "DE": 326,
          "ER": 12,
          "FR": 77,
          "GB": 224,
          "LU": 363,
          "NL": 442,
          "NZ": 139,
          "ML": 1,
          "US": 303
        },
        "createdAt": "2017-01-24T16:12:35+00:00",
        "updatedAt": "2017-01-24T16:12:35+00:00"
      }
    },
    {
      "country": "DE",
      "id": "56bcaa724dab716d288b4567",
      "type": "weiszweinessig",
      "name": "Weißweinessig*",
      "slug": "weiszweinessig",
      "description": null,
      "internalName": "Weißweinessig (home)",
      "shipped": false,
      "imageLink": "https://d3hvwccx09j84u.cloudfront.net/200,200/ingredients/56bcaa724dab716d288b4567-5006d293.png",
      "usage": 87,
      "hasDuplicatedName": null,
      "allergens": [],
      "family": {
        "id": "58877cf3ed71a76e9c03fc4e",
        "type": "vinegar",
        "name": "Essig",
        "slug": "essig",
        "description": null,
        "priority": 0,
        "iconLink": "https://d3hvwccx09j84u.cloudfront.net/200,200/ingredient-families/58877cf3ed71a76e9c03fc4e-487a2c2e.png",
        "usageByCountry": {
          "AT": 946,
          "AU": 556,
          "BE": 739,
          "CA": 272,
          "CH": 185,
          "DE": 877,
          "ER": 16,
          "FR": 209,
          "GB": 406,
          "LU": 884,
          "NL": 855,
          "NZ": 199,
          "ML": 77,
          "US": 710
        },
        "createdAt": "2017-01-24T16:12:35+00:00",
        "updatedAt": "2017-01-24T16:12:35+00:00"
      }
    },
    {
      "country": "DE",
      "id": "554b22f4f8b25e42438b4567",
      "type": "essig",
      "name": "Essig*",
      "slug": "essig",
      "description": null,
      "internalName": "Essig [home]",
      "shipped": false,
      "imageLink": "https://d3hvwccx09j84u.cloudfront.net/200,200/image/554b22f4f8b25e42438b4567.png",
      "usage": 323,
      "hasDuplicatedName": null,
      "allergens": [
        {
          "id": "57962a07b7e8697d4b3052ff",
          "type": "sulphites",
          "name": "Schwefel",
          "slug": "schwefel",
          "description": null,
          "tracesOf": false,
          "triggersTracesOf": false,
          "iconLink": "https://d3hvwccx09j84u.cloudfront.net/0,0/allergens/57962a07b7e8697d4b3052ff-04104ef2.png",
          "usage": 178
        }
      ],
      "family": {
        "id": "58877cf3ed71a76e9c03fc4e",
        "type": "vinegar",
        "name": "Essig",
        "slug": "essig",
        "description": null,
        "priority": 0,
        "iconLink": "https://d3hvwccx09j84u.cloudfront.net/200,200/ingredient-families/58877cf3ed71a76e9c03fc4e-487a2c2e.png",
        "usageByCountry": {
          "AT": 946,
          "AU": 556,
          "BE": 739,
          "CA": 272,
          "CH": 185,
          "DE": 877,
          "ER": 16,
          "FR": 209,
          "GB": 406,
          "LU": 884,
          "NL": 855,
          "NZ": 199,
          "ML": 77,
          "US": 710
        },
        "createdAt": "2017-01-24T16:12:35+00:00",
        "updatedAt": "2017-01-24T16:12:35+00:00"
      }
    },
    {
      "country": "DE",
      "id": "554b6070f8b25e49448b4568",
      "type": "putenbrust",
      "name": "Putenbrust",
      "slug": "putenbrust",
      "description": null,
      "internalName": null,
      "shipped": true,
      "imageLink": "https://d3hvwccx09j84u.cloudfront.net/200,200/image/554b6070f8b25e49448b4568.png",
      "usage": 125,
      "hasDuplicatedName": null,
      "allergens": [],
      "family": {
        "id": "58877cf3ed71a76e9c03fc47",
        "type": "turkey",
        "name": "Truthahn",
        "slug": "truthahn",
        "description": null,
        "priority": 0,
        "iconLink": "https://d3hvwccx09j84u.cloudfront.net/200,200/ingredient-families/58877cf3ed71a76e9c03fc47-151890c5.png",
        "usageByCountry": {
          "AT": 171,
          "AU": 0,
          "BE": 20,
          "CA": 24,
          "CH": 46,
          "DE": 171,
          "ER": 0,
          "FR": 2,
          "GB": 33,
          "LU": 11,
          "NL": 23,
          "NZ": 0,
          "ML": 26,
          "US": 42
        },
        "createdAt": "2017-01-24T16:12:35+00:00",
        "updatedAt": "2017-01-24T16:12:35+00:00"
      }
    },
    {
      "country": "DE",
      "id": "554b3507f8b25ef93e8b4570",
      "type": "cashewkerne",
      "name": "Cashewkerne",
      "slug": "cashewkerne",
      "description": null,
      "internalName": null,
      "shipped": true,
      "imageLink": "https://d3hvwccx09j84u.cloudfront.net/200,200/image/554b3507f8b25ef93e8b4570.png",
      "usage": 98,
      "hasDuplicatedName": null,
      "allergens": [
        {
          "id": "57962a07b7e8697d4b3052f3",
          "type": "maycontaintracesofallergens",
          "name": "kann Spuren von Allergenen enthalten",
          "slug": "kann-spuren-von-allergenen-enthalten",
          "description": null,
          "tracesOf": false,
          "triggersTracesOf": true,
          "iconLink": null,
          "usage": 1649
        }
      ],
      "family": {
        "id": "58877cf3ed71a76e9c03fbe6",
        "type": "nuts",
        "name": "Nüsse",
        "slug": "nusse",
        "description": null,
        "priority": 0,
        "iconLink": "https://d3hvwccx09j84u.cloudfront.net/200,200/ingredient-families/58877cf3ed71a76e9c03fbe6-fd79cfee.png",
        "usageByCountry": {
          "AT": 714,
          "AU": 400,
          "BE": 675,
          "CA": 114,
          "CH": 136,
          "DE": 690,
          "ER": 1,
          "FR": 132,
          "GB": 356,
          "LU": 684,
          "NL": 770,
          "NZ": 120,
          "ML": 72,
          "US": 349
        },
        "createdAt": "2017-01-24T16:12:35+00:00",
        "updatedAt": "2017-01-24T16:12:35+00:00"
      }
    },
    {
      "country": "DE",
      "id": "554b1bf6f8b25eef3e8b4570",
      "type": "ol",
      "name": "Öl*",
      "slug": "ol",
      "description": null,
      "internalName": null,
      "shipped": false,
      "imageLink": "https://d3hvwccx09j84u.cloudfront.net/200,200/image/554b1bf6f8b25eef3e8b4570.png",
      "usage": 1499,
      "hasDuplicatedName": null,
      "allergens": [],
      "family": {
        "id": "58877cf3ed71a76e9c03fbe8",
        "type": "oil",
        "name": "Öl",
        "slug": "ol",
        "description": null,
        "priority": 0,
        "iconLink": "https://d3hvwccx09j84u.cloudfront.net/200,200/ingredient-families/58877cf3ed71a76e9c03fbe8-34c502d3.png",
        "usageByCountry": {
          "AT": 3004,
          "AU": 136,
          "BE": 433,
          "CA": 940,
          "CH": 624,
          "DE": 2780,
          "ER": 171,
          "FR": 109,
          "GB": 4,
          "LU": 555,
          "NL": 503,
          "NZ": 0,
          "ML": 32,
          "US": 978
        },
        "createdAt": "2017-01-24T16:12:35+00:00",
        "updatedAt": "2017-01-24T16:12:35+00:00"
      }
    }
  ],
  "allergens": [
    {
      "id": "57962a07b7e8697d4b3052f9",
      "type": "soya",
      "name": "Soja",
      "slug": "soja",
      "description": null,
      "tracesOf": false,
      "triggersTracesOf": false,
      "iconLink": "https://d3hvwccx09j84u.cloudfront.net/0,0/allergens/57962a07b7e8697d4b3052f9-feb8e168.png",
      "usage": 390
    },
    {
      "id": "57962a07b7e8697d4b3052f5",
      "type": "gluten",
      "name": "Weizen",
      "slug": "weizen",
      "description": null,
      "tracesOf": false,
      "triggersTracesOf": false,
      "iconLink": "https://d3hvwccx09j84u.cloudfront.net/0,0/allergens/57962a07b7e8697d4b3052f5-e20d9ca4.png",
      "usage": 1406
    },
    {
      "id": "57962a07b7e8697d4b3052ff",
      "type": "sulphites",
      "name": "Schwefel",
      "slug": "schwefel",
      "description": null,
      "tracesOf": false,
      "triggersTracesOf": false,
      "iconLink": "https://d3hvwccx09j84u.cloudfront.net/0,0/allergens/57962a07b7e8697d4b3052ff-04104ef2.png",
      "usage": 178
    },
    {
      "id": "57962a07b7e8697d4b3052f3",
      "type": "maycontaintracesofallergens",
      "name": "kann Spuren von Allergenen enthalten",
      "slug": "kann-spuren-von-allergenen-enthalten",
      "description": null,
      "tracesOf": false,
      "triggersTracesOf": true,
      "iconLink": null,
      "usage": 1649
    }
  ],
  "utensils": [
    {
      "id": "57e2674fb7e8697d4b305367",
      "type": "bakingdish",
      "name": "Auflaufform"
    },
    {
      "id": "57e2674fb7e8697d4b305374",
      "type": "stove",
      "name": "Ofen"
    },
    {
      "id": "57e2674fb7e8697d4b3053a1",
      "type": "smallpot",
      "name": "Kleiner Topf"
    },
    {
      "id": "57e2674fb7e8697d4b305382",
      "type": "strainer",
      "name": "Sieb"
    },
    {
      "id": "57e2674fb7e8697d4b305380",
      "type": "smallbowl",
      "name": "Kleine Schale"
    },
    {
      "id": "57e2674fb7e8697d4b30536e",
      "type": "grater",
      "name": "Reibe"
    },
    {
      "id": "57e2674fb7e8697d4b305373",
      "type": "largepan",
      "name": "Große Pfanne"
    },
    {
      "id": "57e2674fb7e8697d4b305376",
      "type": "papertowel",
      "name": "Küchenpapier"
    }
  ],
  "tags": [
    {
      "id": "57d13370b7e8697d4b305318",
      "type": "lactose-free",
      "name": "laktosefrei",
      "slug": "laktosefrei",
      "iconLink": "https://d3hvwccx09j84u.cloudfront.net/200,200/tags/icon-lactose%403x.png",
      "numberOfRecipes": 2675,
      "numberOfRecipesByCountry": {
        "AT": 41,
        "AU": 161,
        "BE": 430,
        "CA": 61,
        "CH": 8,
        "DE": 43,
        "ER": 0,
        "FR": 109,
        "GB": 276,
        "LU": 524,
        "NL": 501,
        "NZ": 0,
        "ML": 45,
        "US": 476
      }
    },
    {
      "id": "57d13370b7e8697d4b305319",
      "type": "spicy",
      "name": "scharf",
      "slug": "scharf",
      "iconLink": "https://d3hvwccx09j84u.cloudfront.net/200,200/tags/icon-spicy%403x.png",
      "numberOfRecipes": 2399,
      "numberOfRecipesByCountry": {
        "AT": 200,
        "AU": 107,
        "BE": 147,
        "CA": 71,
        "CH": 53,
        "DE": 211,
        "ER": 103,
        "FR": 0,
        "GB": 497,
        "LU": 54,
        "NL": 149,
        "NZ": 0,
        "ML": 0,
        "US": 807
      }
    }
  ],
  "cuisines": [
    {
      "id": "57ebbc17b7e8697d4b3053a5",
      "type": "asian",
      "name": "Asiatisch",
      "slug": "asiatisch",
      "iconLink": "https://d3hvwccx09j84u.cloudfront.net/0,0/cuisines/57ebbc17b7e8697d4b3053a5-0483bf75.jpg",
      "usage": 2484
    }
  ],
  "wines": [],
  "marketplaceItems": [],
  "author": null,
  "label": null,
  "yieldType": "servings",
  "yields": [
    {
      "yields": 2,
      "ingredients": [
        {
          "id": "554b23dff8b25ef53e8b456f",
          "amount": 3,
          "unit": "Stück"
        },
        {
          "id": "554b34554dab71a6058b4576",
          "amount": 1,
          "unit": "Stück"
        },
        {
          "id": "554b22cb4dab71c8058b4570",
          "amount": null,
          "unit": "Einheit"
        },
        {
          "id": "554b1c284dab71a9058b456b",
          "amount": null,
          "unit": "Einheit"
        },
        {
          "id": "55b0a135fd2cb9121e8b4567",
          "amount": null,
          "unit": "Einheit"
        },
        {
          "id": "554b3534f8b25ef53e8b4575",
          "amount": 150,
          "unit": "g"
        },
        {
          "id": "554b7f33fd2cb96c628b456a",
          "amount": 1,
          "unit": "Stück"
        },
        {
          "id": "554b1adef8b25ef93e8b456a",
          "amount": 0.5,
          "unit": "Stück"
        },
        {
          "id": "554b7d36fd2cb9d8608b4570",
          "amount": 30,
          "unit": "ml"
        },
        {
          "id": "554b7d614dab71160d8b456b",
          "amount": null,
          "unit": "Einheit"
        },
        {
          "id": "56bcaa724dab716d288b4567",
          "amount": null,
          "unit": "Einheit"
        },
        {
          "id": "554b22f4f8b25e42438b4567",
          "amount": null,
          "unit": "Einheit"
        },
        {
          "id": "554b6070f8b25e49448b4568",
          "amount": 2,
          "unit": "Stück"
        },
        {
          "id": "554b3507f8b25ef93e8b4570",
          "amount": 25,
          "unit": "g"
        },
        {
          "id": "554b1bf6f8b25eef3e8b4570",
          "amount": null,
          "unit": "Einheit"
        }
      ]
    }
  ],
  "steps": [
    {
      "index": 1,
      "instructionsMarkdown": "Vorbereitung: Alle Zutaten und Utensilien bereitstellen. Wasserkocher füllen und anschalten. Obst und Gemüse waschen und putzen. Backofen auf 200 °C Ober-/Unterhitze (180 °C Umluft) vorheizen.\n\nKarotten schälen, dann jeweils einmal quer und einmal längs halbieren. Zwiebel abziehen und ca. 1 cm breite Ringe schneiden. Beides in einer gefetteten Auflaufform gleichmäßig verteilen, mit 1 EL Olivenöl beträufeln, mit Salz und Pfeffer würzen. Auf der mittleren Schiene im Backofen ca. 10 Min. garen.",
      "instructionsHTML": "<p>Vorbereitung: Alle Zutaten und Utensilien bereitstellen. Wasserkocher füllen und anschalten. Obst und Gemüse waschen und putzen. Backofen auf 200 °C Ober-/Unterhitze (180 °C Umluft) vorheizen.</p>\n<p>Karotten schälen, dann jeweils einmal quer und einmal längs halbieren. Zwiebel abziehen und ca. 1 cm breite Ringe schneiden. Beides in einer gefetteten Auflaufform gleichmäßig verteilen, mit 1 EL Olivenöl beträufeln, mit Salz und Pfeffer würzen. Auf der mittleren Schiene im Backofen ca. 10 Min. garen.</p>",
      "instructions": "Vorbereitung: Alle Zutaten und Utensilien bereitstellen. Wasserkocher füllen und anschalten. Obst und Gemüse waschen und putzen. Backofen auf 200 °C Ober-/Unterhitze (180 °C Umluft) vorheizen.\nKarotten schälen, dann jeweils einmal quer und einmal längs halbieren. Zwiebel abziehen und ca. 1 cm breite Ringe schneiden. Beides in einer gefetteten Auflaufform gleichmäßig verteilen, mit 1 EL Olivenöl beträufeln, mit Salz und Pfeffer würzen. Auf der mittleren Schiene im Backofen ca. 10 Min. garen.",
      "timers": [
        {
          "name": "Backofen vorheizen",
          "duration": "PT20M",
          "temperature": 180,
          "temperatureUnit": "C",
          "ovenMode": "PreHeating"
        },
        {
          "name": "Gemüse garen",
          "duration": "PT10M",
          "temperature": 180,
          "temperatureUnit": "C",
          "ovenMode": "HotAir"
        }
      ],
      "images": [
        {
          "link": "https://d3hvwccx09j84u.cloudfront.net/0,0/57567d31f8b25e48148b4568/step_5756e153ddf24.jpg",
          "caption": "Gemüse vorbereiten"
        }
      ],
      "videos": [],
      "ingredients": [
        "554b23dff8b25ef53e8b456f",
        "554b34554dab71a6058b4576",
        "554b22cb4dab71c8058b4570",
        "554b1c284dab71a9058b456b",
        "55b0a135fd2cb9121e8b4567"
      ],
      "utensils": [
        "57e2674fb7e8697d4b305367",
        "57e2674fb7e8697d4b305374"
      ]
    },
    {
      "index": 2,
      "instructionsMarkdown": "Währenddessen: Basmatireis in einem Sieb mit kaltem Wasser abspülen, bis dieses klar hindurchfließt (so wird der Reis fluffiger). 300 ml kochendes Wasser in einen kleinen Topf geben, salzen, einmal aufkochen lassen, Reis einrühren, Deckel aufsetzen und auf niedriger Hitze ca. 10 Min. köcheln lassen. Dann vom Herd nehmen und mindestens 10 Min. abgedeckt ruhen lassen.",
      "instructionsHTML": "<p>Währenddessen: Basmatireis in einem Sieb mit kaltem Wasser abspülen, bis dieses klar hindurchfließt (so wird der Reis fluffiger). 300 ml kochendes Wasser in einen kleinen Topf geben, salzen, einmal aufkochen lassen, Reis einrühren, Deckel aufsetzen und auf niedriger Hitze ca. 10 Min. köcheln lassen. Dann vom Herd nehmen und mindestens 10 Min. abgedeckt ruhen lassen.</p>",
      "instructions": "Währenddessen: Basmatireis in einem Sieb mit kaltem Wasser abspülen, bis dieses klar hindurchfließt (so wird der Reis fluffiger). 300 ml kochendes Wasser in einen kleinen Topf geben, salzen, einmal aufkochen lassen, Reis einrühren, Deckel aufsetzen und auf niedriger Hitze ca. 10 Min. köcheln lassen. Dann vom Herd nehmen und mindestens 10 Min. abgedeckt ruhen lassen.",
      "timers": [
        {
          "name": "Reis zubereiten",
          "duration": "PT10M",
          "temperature": null,
          "temperatureUnit": null,
          "ovenMode": null
        }
      ],
      "images": [],
      "videos": [],
      "ingredients": [
        "554b3534f8b25ef53e8b4575",
        "554b1c284dab71a9058b456b"
      ],
      "utensils": [
        "57e2674fb7e8697d4b3053a1",
        "57e2674fb7e8697d4b305382"
      ]
    },
    {
      "index": 3,
      "instructionsMarkdown": "Für die Glasur: Ingwer schälen und klein hacken. Chili halbieren, Kerne entfernen und fein hacken. Hälfte der Limette fein abreiben, dann Limette halbieren, eine Hälfte entsaften, den Rest in feine Spalten schneiden. In einer kleinen Schüssel ½ EL Honig, 2 EL Wasser, Sojasoße, 1 TL Essig, Limettensaft-und abrieb, Ingwer- und Chilistückchen gründlich miteinander verrühren.",
      "instructionsHTML": "<p>Für die Glasur: Ingwer schälen und klein hacken. Chili halbieren, Kerne entfernen und fein hacken. Hälfte der Limette fein abreiben, dann Limette halbieren, eine Hälfte entsaften, den Rest in feine Spalten schneiden. In einer kleinen Schüssel ½ EL Honig, 2 EL Wasser, Sojasoße, 1 TL Essig, Limettensaft-und abrieb, Ingwer- und Chilistückchen gründlich miteinander verrühren.</p>",
      "instructions": "Für die Glasur: Ingwer schälen und klein hacken. Chili halbieren, Kerne entfernen und fein hacken. Hälfte der Limette fein abreiben, dann Limette halbieren, eine Hälfte entsaften, den Rest in feine Spalten schneiden. In einer kleinen Schüssel ½ EL Honig, 2 EL Wasser, Sojasoße, 1 TL Essig, Limettensaft-und abrieb, Ingwer- und Chilistückchen gründlich miteinander verrühren.",
      "timers": [],
      "images": [
        {
          "link": "https://d3hvwccx09j84u.cloudfront.net/0,0/57567d31f8b25e48148b4568/step_5756e1541f375.jpg",
          "caption": "Glasur vorbereiten"
        }
      ],
      "videos": [],
      "ingredients": [
        "554b7f33fd2cb96c628b456a",
        "554b1adef8b25ef93e8b456a",
        "554b7d36fd2cb9d8608b4570",
        "554b7d614dab71160d8b456b",
        "56bcaa724dab716d288b4567",
        "554b22f4f8b25e42438b4567"
      ],
      "utensils": [
        "57e2674fb7e8697d4b305380",
        "57e2674fb7e8697d4b30536e"
      ]
    },
    {
      "index": 4,
      "instructionsMarkdown": "Putenbrust mit Küchenpapier trocken tupfen. In einer großen Pfanne ½ EL Öl erwärmen und darin je Seite ca. 2 Min. scharf anbraten. Anschließend Putenbrust zum Gemüse in die Auflaufform geben und alles mit der Glasur übergießen. Alles vorsichtig vermischen und 10 – 15 Min. weiter garen. Für die letzten 5 Min. der Garzeit Cashewkerne unterheben und alles fertig garen.",
      "instructionsHTML": "<p>Putenbrust mit Küchenpapier trocken tupfen. In einer großen Pfanne ½ EL Öl erwärmen und darin je Seite ca. 2 Min. scharf anbraten. Anschließend Putenbrust zum Gemüse in die Auflaufform geben und alles mit der Glasur übergießen. Alles vorsichtig vermischen und 10 – 15 Min. weiter garen. Für die letzten 5 Min. der Garzeit Cashewkerne unterheben und alles fertig garen.</p>",
      "instructions": "Putenbrust mit Küchenpapier trocken tupfen. In einer großen Pfanne ½ EL Öl erwärmen und darin je Seite ca. 2 Min. scharf anbraten. Anschließend Putenbrust zum Gemüse in die Auflaufform geben und alles mit der Glasur übergießen. Alles vorsichtig vermischen und 10 – 15 Min. weiter garen. Für die letzten 5 Min. der Garzeit Cashewkerne unterheben und alles fertig garen.",
      "timers": [
        {
          "name": "Putenbrust mit Gemüse garen",
          "duration": "PT10M",
          "temperature": 180,
          "temperatureUnit": "C",
          "ovenMode": "HotAir"
        },
        {
          "name": "Mit Cashewkernen fertig garen",
          "duration": "PT05M",
          "temperature": 180,
          "temperatureUnit": "C",
          "ovenMode": "HotAir"
        }
      ],
      "images": [
        {
          "link": "https://d3hvwccx09j84u.cloudfront.net/0,0/57567d31f8b25e48148b4568/step_5756e15432b53.jpg",
          "caption": "Glasur über Zutaten geben"
        }
      ],
      "videos": [],
      "ingredients": [
        "554b6070f8b25e49448b4568",
        "554b3507f8b25ef93e8b4570",
        "554b1bf6f8b25eef3e8b4570"
      ],
      "utensils": [
        "57e2674fb7e8697d4b305373",
        "57e2674fb7e8697d4b305376"
      ]
    },
    {
      "index": 5,
      "instructionsMarkdown": "Basmatireis mit einer Gabel ein wenig auflockern und auf Tellern verteilen. Glasierte Putenbrust mit Gemüse darauf anrichten und genießen.",
      "instructionsHTML": "<p>Basmatireis mit einer Gabel ein wenig auflockern und auf Tellern verteilen. Glasierte Putenbrust mit Gemüse darauf anrichten und genießen.</p>",
      "instructions": "Basmatireis mit einer Gabel ein wenig auflockern und auf Tellern verteilen. Glasierte Putenbrust mit Gemüse darauf anrichten und genießen.",
      "timers": [],
      "images": [
        {
          "link": "https://d3hvwccx09j84u.cloudfront.net/0,0/57567d31f8b25e48148b4568/step_5756e15446d67.jpg",
          "caption": "Basmatireis auflockern"
        }
      ],
      "videos": [],
      "ingredients": [],
      "utensils": []
    }
  ],
  "averageRating": 3.3,
  "ratingsCount": 1063,
  "favoritesCount": 619,
  "active": true,
  "highlighted": false,
  "isDinnerToLunch": false,
  "isExcludedFromIndex": false,
  "isPremium": false,
  "websiteUrl": "https://www.hellofresh.de/recipes/pikant-glasierte-putenbrust-mit-ofen-mohren-57567d31f8b25e48148b4568",
  "clonedFrom": null,
  "canonical": "5756c95af8b25e07528b4567",
  "canonicalLink": "https://www.hellofresh.de/recipes/tm-pikant-glasierte-putenbrust-mit-ofen-mohren-5756c95af8b25e07528b4567"
}
